{
  "id": "cmqt2nwar000t12t04feue7zh",
  "titleEn": "Cattle market update: Screwworm, drought and strong beef prices",
  "titleZh": "畜牧市场动态：螺旋蝇、干旱与强劲牛肉价格",
  "url": "https://www.beefmagazine.com/market-news/cattle-market-update-screwworm-drought-and-strong-beef-prices",
  "summaryZh": "本文聚焦当前畜牧市场三大关键因素：15例螺旋蝇病例中3例已解除警报，53%的牛群受干旱影响，5月零售牛肉价格同比上涨13%。值得关注的是，这些因素如何共同影响市场供需与价格走势，为畜牧从业者提供决策参考。",
  "translationZh": null,
  "publishedAt": "2026-06-22T20:19:37.000Z",
  "source": {
    "name": "Beef Magazine",
    "nameZh": "肉牛杂志",
    "tier": "T2"
  },
  "species": "cattle",
  "category": "livestock",
  "subcategory": "cattle",
  "techTags": "",
  "qualityScore": 18,
  "isHot": false,
  "multiSourceCount": 1,
  "contentFull": "",
  "images": [],
  "author": "",
  "featuredReason": "",
  "contentHtml": "Three of 15 NWS cases now inactive. 53% of cattle inventory impacted by drought. May retail beef price up 13% from a year ago.",
  "scrapeMethod": "rss"
}