{
  "id": "cmqz24pcj007hdidxvb1a2zjr",
  "titleEn": "Tar spot detected early in Kansas; scout cornfields now",
  "titleZh": null,
  "url": "https://www.farmprogress.com/crop-disease/tar-spot-detected-early-in-kansas-scout-cornfields-now",
  "summaryZh": null,
  "translationZh": null,
  "publishedAt": "2026-06-25T07:00:00.000Z",
  "source": {
    "name": "Farm Progress",
    "nameZh": "农业进展",
    "tier": "T2"
  },
  "species": "aggtech",
  "category": null,
  "subcategory": null,
  "techTags": "",
  "qualityScore": 0,
  "isHot": false,
  "multiSourceCount": 1,
  "contentFull": "",
  "images": [],
  "author": "",
  "featuredReason": "",
  "contentHtml": "Scouting fields early and creating a fungicide plan can help you protect yields.",
  "scrapeMethod": "rss"
}