{
  "id": "cmqz24p360063didxx4i08sxf",
  "titleEn": "Farm marriage proposals create lasting memories",
  "titleZh": null,
  "url": "https://www.farmprogress.com/farm-life/farm-proposals-create-lasting-memories-for-couples-who-share-love-of-land-and-agriculture",
  "summaryZh": null,
  "translationZh": null,
  "publishedAt": "2026-06-29T07:00:00.000Z",
  "source": {
    "name": "Farm Progress",
    "nameZh": "农业进展",
    "tier": "T2"
  },
  "species": "aggtech",
  "category": null,
  "subcategory": null,
  "techTags": "",
  "qualityScore": 0,
  "isHot": false,
  "multiSourceCount": 1,
  "contentFull": "",
  "images": [],
  "author": "",
  "featuredReason": "",
  "contentHtml": "Bow Creek Chronicles: After 28 years of marriage, I know from experience that on-farm marriage proposals are often simple but memorable.",
  "scrapeMethod": "rss"
}