{
  "id": "cmrvh8tzr007b94umxd950g4u",
  "titleEn": "陕西陆基循环水鲈鱼养殖车间施工中！",
  "titleZh": "陕西陆基循环水鲈鱼养殖车间施工中！",
  "url": "https://mp.weixin.qq.com/s/CArxcvk4iG-GABBwSjqwEg",
  "summaryZh": "陕西正在建设陆基循环水鲈鱼养殖车间，由青岛帮邦智能科技提供一站式解决方案，涵盖工厂化循环水养殖装备、水产物联网设备和信息化技术。该公司提供从规划设计到养殖运营的全链条服务，并免费提供循环水养殖系统资料。该项目体现了智慧水产养殖中自动化、物联网技术的应用，但新闻内容偏重商业推广，技术细节和实际效果信息不足。",
  "translationZh": "",
  "featuredReason": "该新闻展示了智慧水产养殖的落地案例，涉及循环水系统与物联网技术，对关注工厂化养殖的从业者具有实践参考价值，但创新性和行业影响力一般。",
  "publishedAt": "2026-05-13T07:17:11.000Z",
  "source": {
    "name": "智慧水产",
    "nameZh": "智慧水产",
    "tier": "T1.5",
    "sourceType": "微信公众号"
  },
  "species": "general",
  "category": "aggtech",
  "subcategory": "general",
  "techTags": "",
  "qualityScore": 46,
  "isHot": false,
  "multiSourceCount": 1,
  "isFeatured": false,
  "contentFull": "",
  "images": [],
  "author": "",
  "contentHtml": "青岛帮邦智能科技有限公司，致力于为工厂化、无人化、智慧化水产养殖提供一站式解决方案，业务覆盖工厂化循环水养殖装备生产、水产物联网设备生产和信息化技术开发。\n\n提供规划设计、建设安装、技术咨询、改造升级、养殖运营等服务。\n\n请添加微信沟通 15965423396！免费领取循环水养殖系统资料。",
  "scrapeMethod": "wechat_api"
}